{
  "api_definition": {
    "name": "Products API #otel-demo",
    "slug": "products",
    "api_id": "products-api",
    "org_id": "1",
    "use_keyless": true,
    "proxy": {
      "listen_path": "/api/products",
      "target_url": "env://FRONTEND_URL",
      "strip_listen_path": false
    },
    "active": true,
    "version_data": {
      "not_versioned": true,
      "default_version": "",
      "versions": {
        "Default": {
          "name": "Default",
          "use_extended_paths": true,
          "extended_paths": {
            "track_endpoints": [
              {
                "disabled": false,
                "path": "{id}",
                "method": "GET"
              }
            ]
          }
        }
      }
    }
  }
}
